mollview/__init__.py
mollview/__main__.py
mollview-1.0.0.dist-info/entry_points.txt
mollview-1.0.0.dist-info/LICENSE
mollview-1.0.0.dist-info/WHEEL
mollview-1.0.0.dist-info/METADATA
mollview-1.0.0.dist-info/RECORD
